pypho/__init__.py
pypho/camera.py
pypho/graphics.py
pypho/rock_texture.vti
pypho/target.py
pypho-0.0.4.dist-info/licenses/Licence_CeCILL-B_V1-en.txt
pypho-0.0.4.dist-info/METADATA
pypho-0.0.4.dist-info/WHEEL
pypho-0.0.4.dist-info/top_level.txt
pypho-0.0.4.dist-info/RECORD
