Metadata-Version: 2.4
Name: pypho
Version: 0.0.4
Summary: Interactive photogrammetric design for geological objects
Author-email: Gautier Laurent <gautier.laurent@univ-orleans.fr>
Project-URL: Homepage, https://github.com/GeoISTO/PyPho
Keywords: photography,photogrammetry,geology
Classifier: Programming Language :: Python
Classifier: Programming Language :: Python :: 3
Classifier: Development Status :: 2 - Pre-Alpha
Classifier: Framework :: Jupyter
Classifier: Intended Audience :: Science/Research
Classifier: Natural Language :: English
Requires-Python: >=3.10
License-File: Licence_CeCILL-B_V1-en.txt
Requires-Dist: pyvista
Requires-Dist: pandas
Requires-Dist: scipy
Requires-Dist: meshio
Requires-Dist: trame
Requires-Dist: vtk>=9.1
Requires-Dist: trame-vtk
Requires-Dist: trame-vuetify
Requires-Dist: colorcet
Provides-Extra: nb
Requires-Dist: jupyter; extra == "nb"
Dynamic: license-file
